kyotostaily_test1/__init__.py
kyotostaily_test1/converter.py
kyotostaily_test1-1.0.3.dist-info/LICENSE
kyotostaily_test1-1.0.3.dist-info/METADATA
kyotostaily_test1-1.0.3.dist-info/WHEEL
kyotostaily_test1-1.0.3.dist-info/top_level.txt
kyotostaily_test1-1.0.3.dist-info/RECORD
