Metadata-Version: 2.1
Name: kyotostaily-test1
Version: 1.0.3
Summary: Test package for distribution
Home-page: UNKNOWN
Author: kyotostaily
Author-email: kyotostaily@naver.com
License: UNKNOWN
Keywords: GIFCONVERTER,gifconverter
Platform: UNKNOWN
Classifier: Programming Language :: Python :: 3
Classifier: License :: OSI Approved :: MIT License
Classifier: Operating System :: OS Independent
Requires-Python: >=3
License-File: LICENSE
Requires-Dist: pillow
